ezkl-100.100.101.dist-info/METADATA
ezkl-100.100.101.dist-info/WHEEL
ezkl/__init__.py
ezkl/ezkl.abi3.so
ezkl-100.100.101.dist-info/RECORD
